{"stat.leaveGame":18,"stat.killEntity.Parrot":3,"stat.useItem.cfm.stone_path":28,"stat.mineBlock.ic2.rubber_wood":7,"stat.killEntity.divinerpg.cave_crawler":41,"stat.mineBlock.minecraft.sandstone":14,"stat.mineBlock.minecraft.stained_glass":3,"stat.useItem.minecraft.planks":2,"stat.pickup.minecraft.glowstone_dust":6,"stat.pickup.minecraft.porkchop":3,"stat.killEntity.divinerpg.king_crab":2,"stat.mineBlock.divinerpg.realmite_ore":59,"stat.mineBlock.minecraft.stone_brick_stairs":10,"stat.pickup.minecraft.rotten_flesh":102,"stat.pickup.minecraft.sand":96,"stat.craftItem.minecraft.stone_axe":17,"stat.pickup.minecraft.cobblestone_wall":9,"stat.killEntity.Enderman":3,"stat.craftItem.minecraft.stone_sword":1,"stat.mineBlock.minecraft.sand":104,"stat.killEntity.Witch":39,"stat.drop.minecraft.sand":1,"stat.useItem.ic2.bronze_axe":224,"stat.pickup.minecraft.stained_hardened_clay":1,"stat.mineBlock.minecraft.vine":36,"stat.furnaceInteraction":116,"stat.killEntity.ZombieVillager":1,"stat.pickup.divinerpg.bloodgem":1,"stat.craftItem.divinerpg.realmite_leggings":1,"stat.mineBlock.better_diving.creepvine_seed":1,"stat.killEntity.divinerpg.jungle_dramcryx":7,"stat.useItem.minecraft.cooked_mutton":13,"stat.pickup.minecraft.hay_block":4,"stat.pickup.ic2.bronze_helmet":1,"stat.pickup.minecraft.potion":4,"stat.useItem.ic2.sapling":1,"stat.useItem.minecraft.wheat_seeds":388,"stat.drop.divinerpg.rupee_rapier":1,"stat.mineBlock.minecraft.brick_stairs":1,"stat.craftItem.divinerpg.realmite_boots":1,"stat.drop.minecraft.jungle_boat":1,"stat.mineBlock.ic2.leaves":18,"stat.useItem.minecraft.dye":2,"stat.deaths":82,"stat.craftItem.divinerpg.realmite_chestplate":3,"stat.playOneMinute":947805,"stat.useItem.minecraft.jungle_stairs":1,"stat.pickup.minecraft.iron_bars":1,"stat.drop.minecraft.torch":4,"stat.mineBlock.minecraft.tallgrass":200,"stat.craftItem.minecraft.cooked_mutton":3,"stat.pickup.minecraft.cooked_mutton":3,"stat.chestOpened":272,"stat.pickup.minecraft.pumpkin":18,"stat.craftItem.minecraft.sign":3,"stat.pickup.divinerpg.realmite_ingot":41,"stat.useItem.minecraft.stone":710,"stat.pickup.minecraft.arrow":62,"stat.craftItem.divinerpg.cyclopsian_staff":1,"stat.pickup.minecraft.wooden_pressure_plate":1,"stat.killEntity.divinerpg.rotatick":34,"stat.craftItem.minecraft.coal":692,"stat.pickup.minecraft.brick_stairs":1,"stat.fallOneCm":371478,"stat.drop.minecraft.dye":1,"stat.pickup.minecraft.melon_seeds":1,"stat.crouchOneCm":224755,"stat.craftItem.divinerpg.realmite_pickaxe":1,"stat.craftItem.minecraft.chest":8,"stat.craftItem.minecraft.iron_ingot":9,"stat.pickup.minecraft.melon":7,"stat.killEntity.divinerpg.pumpkin_spider":12,"stat.craftingTableInteraction":68,"stat.mineBlock.minecraft.wooden_pressure_plate":1,"stat.mineBlock.ic2.resource":193,"stat.pickup.minecraft.feather":6,"stat.pickup.minecraft.dye":122,"stat.pickup.minecraft.planks":27,"stat.killEntity.divinerpg.cyclops":28,"stat.pickup.minecraft.wheat_seeds":462,"stat.mineBlock.minecraft.gravel":14,"stat.useItem.minecraft.stone_pickaxe":525,"stat.useItem.minecraft.stone_sword":202,"stat.craftItem.minecraft.iron_leggings":1,"stat.craftItem.cfm.stone_path":72,"stat.entityKilledBy.divinerpg.jungle_dramcryx":1,"stat.mineBlock.minecraft.dirt":3274,"stat.pickup.minecraft.record_11":1,"stat.useItem.minecraft.torch":298,"stat.useItem.minecraft.bread":51,"stat.pickup.minecraft.crafting_table":3,"stat.useItem.minecraft.log":23,"stat.useItem.minecraft.cobblestone":245,"stat.craftItem.minecraft.crafting_table":2,"stat.mineBlock.better_diving.seagrass":1,"stat.pickup.minecraft.log":1756,"stat.drop.minecraft.sapling":1,"stat.pickup.minecraft.sapling":211,"stat.pickup.minecraft.wooden_door":3,"stat.pickup.minecraft.apple":30,"stat.craftItem.minecraft.planks":384,"stat.useItem.minecraft.wooden_pressure_plate":1,"stat.pickup.minecraft.book":156,"stat.useItem.minecraft.stonebrick":43,"stat.mineBlock.minecraft.log":1596,"stat.sneakTime":59890,"stat.pickup.minecraft.wool":2,"stat.pickup.ic2.sapling":2,"stat.useItem.minecraft.wooden_axe":15,"stat.pickup.minecraft.yellow_flower":6,"stat.useItem.divinerpg.rupee_rapier":1291,"stat.drop.minecraft.wooden_axe":1,"stat.drop.minecraft.pumpkin":1,"stat.pickup.minecraft.bone":61,"stat.craftItem.minecraft.jungle_boat":2,"stat.useItem.minecraft.iron_axe":81,"stat.mineBlock.minecraft.cobblestone":44,"stat.mineBlock.minecraft.pumpkin":5,"stat.useItem.divinerpg.realmite_pickaxe":1346,"stat.mineBlock.minecraft.yellow_flower":1,"stat.entityKilledBy.Witch":3,"stat.craftItem.minecraft.stone_brick_stairs":148,"stat.pickup.divinerpg.terran_shards":11,"stat.pickup.divinerpg.crab_claw":12,"stat.swimOneCm":141814,"stat.pickup.divinerpg.cyclops_eye_shards":18,"stat.climbOneCm":110581,"stat.entityKilledBy.divinerpg.crab":2,"stat.pickup.ic2.jetpack_electric":1,"stat.drop.minecraft.cobblestone":2,"stat.entityKilledBy.mutantbeasts.mutant_zombie":3,"stat.useItem.minecraft.dirt":307,"stat.useItem.minecraft.cookie":171,"stat.useItem.minecraft.stone_slab2":65,"stat.pickup.minecraft.bow":4,"stat.craftItem.divinerpg.realmite_ingot":30,"stat.useItem.minecraft.jungle_boat":3,"stat.craftItem.minecraft.furnace":1,"stat.craftItem.divinerpg.rupee_rapier":1,"stat.entityKilledBy.mutantbeasts.mutant_enderman":4,"stat.craftItem.minecraft.iron_boots":2,"stat.craftItem.minecraft.stone_pickaxe":4,"stat.pickup.minecraft.cobblestone":3884,"stat.useItem.minecraft.stone_shovel":209,"stat.flyOneCm":1448778,"stat.pickup.minecraft.sandstone":14,"stat.pickup.minecraft.glass_bottle":14,"stat.craftItem.ic2.ingot":13,"stat.drop.minecraft.wheat_seeds":8,"stat.useItem.minecraft.cooked_beef":54,"stat.pickup.minecraft.cactus":8,"stat.entityKilledBy.divinerpg.cave_crawler":1,"stat.pickup.minecraft.redstone":8,"stat.mineBlock.minecraft.iron_ore":77,"stat.timeSinceDeath":21,"stat.pickup.ic2.bronze_boots":1,"stat.useItem.minecraft.sign":2,"stat.pickup.minecraft.mutton":3,"stat.pickup.minecraft.mossy_cobblestone":1,"stat.craftItem.minecraft.stonebrick":272,"stat.entityKilledBy.divinerpg.pumpkin_spider":2,"stat.pickup.divinerpg.jungle_shards":8,"stat.pickup.minecraft.stonebrick":66,"stat.drop.minecraft.dirt":1,"stat.useItem.minecraft.cooked_porkchop":3,"stat.pickup.ic2.bronze_chestplate":1,"stat.craftItem.divinerpg.palavence":2,"stat.mineBlock.minecraft.coal_ore":567,"stat.killEntity.Creeper":14,"stat.craftItem.minecraft.stone_hoe":2,"stat.talkedToVillager":14,"stat.pickup.minecraft.string":83,"stat.craftItem.minecraft.jungle_stairs":4,"stat.mineBlock.minecraft.ladder":2,"stat.entityKilledBy.Skeleton":6,"stat.craftItem.minecraft.stone_slab2":0,"stat.killEntity.Squid":1,"stat.sprintOneCm":1351358,"stat.craftItem.minecraft.stick":724,"stat.craftItem.minecraft.wooden_axe":1,"stat.pickup.ic2.resource":193,"stat.craftItem.minecraft.stone":322,"stat.pickup.minecraft.grass":1,"stat.mineBlock.minecraft.crafting_table":3,"stat.pickup.divinerpg.aquatic_pellets":1,"stat.craftItem.minecraft.wooden_pressure_plate":1,"stat.killEntity.divinerpg.crab":21,"stat.entityKilledBy.Creeper":2,"stat.pickup.minecraft.sugar":8,"stat.mineBlock.minecraft.planks":29,"stat.pickup.better_diving.peeper":1,"stat.drop":65,"stat.entityKilledBy.divinerpg.rotatick":2,"stat.killEntity.Sheep":2,"stat.useItem.minecraft.ladder":122,"stat.entityKilledBy.mutantbeasts.mutant_creeper":2,"stat.pickup.ic2.bronze_axe":1,"stat.killEntity.Zombie":77,"stat.craftItem.minecraft.dye":24,"stat.drop.minecraft.bread":7,"stat.mineBlock.minecraft.gold_ore":5,"stat.diveOneCm":131333,"stat.pickup.minecraft.wheat":245,"stat.craftItem.minecraft.ladder":240,"stat.pickup.minecraft.gravel":14,"stat.craftItem.minecraft.cooked_porkchop":3,"stat.drop.better_diving.peeper":1,"stat.pickup.minecraft.stone_axe":2,"stat.useItem.minecraft.apple":25,"stat.useItem.minecraft.potion":1,"stat.pickup.ic2.te":1,"stat.useItem.minecraft.rotten_flesh":1,"stat.pickup.minecraft.stone_brick_stairs":10,"stat.jump":11597,"stat.pickup.minecraft.fence":1,"stat.pickup.minecraft.coal":567,"stat.pickup.minecraft.iron_ingot":21,"stat.useItem.minecraft.stone_axe":237,"stat.entityKilledBy.divinerpg.king_crab":2,"stat.pickup.minecraft.gunpowder":31,"stat.craftItem.minecraft.bread":34,"stat.entityKilledBy.CaveSpider":2,"stat.pickup.minecraft.spider_eye":30,"stat.craftItem.minecraft.torch":492,"stat.pickup.minecraft.dirt":3188,"stat.craftItem.minecraft.iron_helmet":2,"stat.pickup.divinerpg.realmite_ore":59,"stat.pickup.minecraft.iron_ore":74,"stat.boatOneCm":331320,"stat.useItem.minecraft.sapling":129,"stat.pickup.minecraft.gold_ore":5,"stat.mineBlock.minecraft.lapis_ore":12,"stat.killEntity.mutantbeasts.mutant_creeper":1,"stat.pickup.divinerpg.healing_stone":1,"stat.pickup.minecraft.cookie":20,"stat.pickup.minecraft.iron_axe":1,"stat.damageTaken":38363,"stat.useItem.minecraft.stone_brick_stairs":156,"stat.mineBlock.minecraft.torch":42,"stat.mineBlock.minecraft.melon_block":1,"stat.mineBlock.minecraft.sapling":18,"stat.pickup.better_diving.creepvine":1,"stat.pickup.minecraft.ender_eye":2,"stat.pickup.ic2.rubber_wood":7,"stat.pickup.ic2.bronze_leggings":1,"stat.killEntity.CaveSpider":16,"stat.pickup.minecraft.bed":4,"stat.entityKilledBy.Zombie":4,"stat.damageDealt":100675,"stat.craftItem.minecraft.glass":20,"stat.sleepInBed":56,"stat.killEntity.Pig":1,"stat.killEntity.divinerpg.jungle_bat":2,"stat.craftItem.minecraft.stone_shovel":1,"stat.pickup.minecraft.boat":1,"stat.walkOneCm":3000770,"stat.animalsBred":6,"stat.entityKilledBy.divinerpg.cyclops":1,"stat.playerKills":7,"stat.useItem.minecraft.chest":5,"stat.killEntity.peeper":1,"stat.pickup.divinerpg.rupee_rapier":1,"stat.pickup.minecraft.stick":53,"stat.killEntity.divinerpg.saguaro_worm":2,"stat.craftItem.divinerpg.realmite_helmet":1,"stat.pickup.minecraft.stone":688,"stat.craftItem.minecraft.iron_chestplate":1,"stat.pickup.minecraft.ender_pearl":7,"stat.pickup.minecraft.ladder":66,"stat.pickup.minecraft.cooked_beef":14,"stat.craftItem.divinerpg.cyclops_eye":1,"stat.pickup.minecraft.gold_ingot":12,"stat.killEntity.Skeleton":47,"stat.mineBlock.minecraft.stonebrick":5,"stat.drop.minecraft.cookie":33,"stat.killEntity.Spider":23,"stat.pickup.minecraft.bread":3,"stat.craftItem.minecraft.cookie":184,"stat.mobKills":383,"stat.useItem.ic2.diamond_drill":7001,"stat.mineBlock.minecraft.bookshelf":51,"stat.pickup.minecraft.diamond":36,"stat.mineBlock.minecraft.leaves":118,"stat.pickup.minecraft.torch":123,"stat.drop.minecraft.stone_axe":2,"stat.mineBlock.minecraft.hay_block":2,"stat.pickup.minecraft.jungle_boat":4,"stat.mineBlock.minecraft.stone":4684}